toxiproxy/__init__.py
toxiproxy/api.py
toxiproxy/exceptions.py
toxiproxy/proxy.py
toxiproxy/server.py
toxiproxy/toxic.py
toxiproxy/utils.py
toxiproxy_python-0.1.1.dist-info/LICENSE
toxiproxy_python-0.1.1.dist-info/METADATA
toxiproxy_python-0.1.1.dist-info/WHEEL
toxiproxy_python-0.1.1.dist-info/top_level.txt
toxiproxy_python-0.1.1.dist-info/RECORD
